mlflow_tclake_plugin/__init__.py
mlflow_tclake_plugin/tclake_store.py
mlflow_tclake_plugin-3.0.5.dist-info/licenses/LICENSE.txt
mlflow_tclake_plugin-3.0.5.dist-info/METADATA
mlflow_tclake_plugin-3.0.5.dist-info/WHEEL
mlflow_tclake_plugin-3.0.5.dist-info/entry_points.txt
mlflow_tclake_plugin-3.0.5.dist-info/top_level.txt
mlflow_tclake_plugin-3.0.5.dist-info/RECORD
