Metadata-Version: 2.4
Name: mlflow-tclake-plugin
Version: 3.0.5
Summary: Tclake plugin for MLflow
License-File: LICENSE.txt
Requires-Dist: mlflow>=3.1.0
Requires-Dist: tencentcloud-sdk-python-common>=3.0.1478
Dynamic: license-file
Dynamic: requires-dist
Dynamic: summary
